nefertem_profiling_ydata_profiling/__init__.py
nefertem_profiling_ydata_profiling/builder.py
nefertem_profiling_ydata_profiling/plugin.py
nefertem_profiling_ydata_profiling/reader.py
nefertem_profiling_ydata_profiling/utils.py
nefertem_profiling_ydata_profiling-2.0.2.dist-info/METADATA
nefertem_profiling_ydata_profiling-2.0.2.dist-info/WHEEL
nefertem_profiling_ydata_profiling-2.0.2.dist-info/top_level.txt
nefertem_profiling_ydata_profiling-2.0.2.dist-info/RECORD
